homie_power_supply_node/__init__.py
homie_power_supply_node-0.1.2.dist-info/WHEEL
homie_power_supply_node-0.1.2.dist-info/METADATA
homie_power_supply_node-0.1.2.dist-info/RECORD
