Metadata-Version: 2.1
Name: homie-power-supply-node
Version: 0.1.2
Summary: homie-power-supply-node is a Python package that uses homie-spec to provide a homie node implementation that can be used to create Homie-compliant messages from your power supply device.
Home-page: https://github.com/Qu4tro/homie-power-supply-node/
License: MIT
Keywords: homie,mqtt
Author: Xavier Francisco
Author-email: xavier.n.francisco@gmail.com
Requires-Python: >=3.6,<4.0
Classifier: License :: OSI Approved :: MIT License
Classifier: Programming Language :: Python :: 3
Classifier: Programming Language :: Python :: 3.6
Classifier: Programming Language :: Python :: 3.7
Classifier: Programming Language :: Python :: 3.8
Requires-Dist: homie-spec (>=0.4.0,<0.5.0)
Project-URL: Repository, https://github.com/Qu4tro/homie-power-supply-node/
